ecactusecos/__init__.py
ecactusecos/const.py
ecactusecos/ecactusecos.py
ecactusecos/exceptions.py
ecactus_ecos_client-0.1.4.dist-info/LICENSE
ecactus_ecos_client-0.1.4.dist-info/METADATA
ecactus_ecos_client-0.1.4.dist-info/WHEEL
ecactus_ecos_client-0.1.4.dist-info/top_level.txt
ecactus_ecos_client-0.1.4.dist-info/RECORD
