Metadata-Version: 2.1
Name: ecactus-ecos-client
Version: 0.1.4
Summary: Client for Ecactus ECOS
Home-page: https://github.com/sjhoeksma/ecactus-ecos-client
Author: S.J.Hoeksma
Author-email: 
Classifier: Intended Audience :: Developers
Classifier: License :: OSI Approved :: Apache Software License
Classifier: Operating System :: OS Independent
Classifier: Programming Language :: Python :: 3
Classifier: Topic :: Home Automation
Requires-Python: >=3.10
License-File: LICENSE
